azure/search/__init__.py
azure/search/_version.py
azure/search/aio.py
azure/search/_index/__init__.py
azure/search/_index/_credential.py
azure/search/_index/_index_documents_batch.py
azure/search/_index/_paging.py
azure/search/_index/_queries.py
azure/search/_index/_search_index_client.py
azure/search/_index/_generated/__init__.py
azure/search/_index/_generated/_configuration.py
azure/search/_index/_generated/_search_index_client.py
azure/search/_index/_generated/aio/__init__.py
azure/search/_index/_generated/aio/_configuration_async.py
azure/search/_index/_generated/aio/_search_index_client_async.py
azure/search/_index/_generated/aio/operations_async/__init__.py
azure/search/_index/_generated/aio/operations_async/_documents_operations_async.py
azure/search/_index/_generated/models/__init__.py
azure/search/_index/_generated/models/_models.py
azure/search/_index/_generated/models/_models_py3.py
azure/search/_index/_generated/models/_search_index_client_enums.py
azure/search/_index/_generated/operations/__init__.py
azure/search/_index/_generated/operations/_documents_operations.py
azure/search/_index/aio/__init__.py
azure/search/_index/aio/_paging.py
azure/search/_index/aio/_search_index_client_async.py
azure_search-1.0.0b2.dist-info/LICENSE.txt
azure_search-1.0.0b2.dist-info/METADATA
azure_search-1.0.0b2.dist-info/WHEEL
azure_search-1.0.0b2.dist-info/top_level.txt
azure_search-1.0.0b2.dist-info/RECORD
